{
  "folders": [
    {
      "name": "nonprofit-advocacy-orgs",
      "bookmarks": [
        {
          "url": "https://aclu-md.org/press_room/81",
          "title": "ACLU Opposes MTA Program Installing Pervasive Audio Surveillance of Riders as Significant Invasion of Privacy - ACLU of Maryland"
        },
        {
          "url": "https://fundforsharedinsight.org/",
          "title": "Foundations Advancing Listening & Feedback in Philanthropy | Fund for Shared Insight"
        },
        {
          "url": "https://globaltiesus.org/",
          "title": "Global Ties U.S. : Global Ties U.S."
        },
        {
          "url": "https://www.lookingoutfoundation.org/",
          "title": "LOF"
        },
        {
          "url": "https://www.naacp.org/",
          "title": "NAACP | Leading the Fight to End Racial Inequality"
        },
        {
          "url": "https://oakfnd.org/",
          "title": "Oak Foundation - Through our grant-making, we support others to make the world a safer, fairer, and more sustainable place to live."
        },
        {
          "url": "https://oceankind.org",
          "title": "Oceankind.org"
        },
        {
          "url": "https://prginc.org/",
          "title": "PRG, Inc."
        },
        {
          "url": "https://wfp.org",
          "title": "UN World Food Programme (WFP)"
        },
        {
          "url": "https://veteransgrowingamerica.com/",
          "title": "Veterans Growing America"
        },
        {
          "url": "https://womenwatchafrika.org/",
          "title": "Women Watch Afrika - Eliminating all forms of discrimination against women."
        },
        {
          "url": "https://www.ywcampls.org/",
          "title": "YWCA Minneapolis | Eliminating Racism | Empowering Women"
        }
      ],
      "count": 12
    },
    {
      "name": "global-news-media",
      "bookmarks": [
        {
          "url": "https://www.woodtv.com/news/alibis-ignored-the-jeff-titus-case/",
          "title": "Alibis Ignored: The Jeff Titus Case"
        },
        {
          "url": "https://www.guinnessworldrecords.com/news/2023/2/dog-with-a-tongue-lengthier-than-a-popsicle-stick-confirmed-as-longest-736653",
          "title": "Dog with a tongue lengthier than a popsicle stick confirmed as longest | Guinness World Records"
        },
        {
          "url": "https://apnews.com/hub/europe",
          "title": "Europe News | Breaking European News Today | AP News"
        },
        {
          "url": "https://actions.fullfact.org/petitions/mps-owe-us-truth/",
          "title": "Full Fact"
        },
        {
          "url": "https://arabpress.com/saudi-aid-agency-chief-meets-mexican-envoy-to-saudi-arabia",
          "title": "Saudi aid agency chief meets Mexican envoy to Saudi Arabia - Arab Press"
        },
        {
          "url": "https://www.theguardian.com/international",
          "title": "Latest news, sport and opinion from the Guardian"
        },
        {
          "url": "https://www.latribunahoy.com/tag/jornadas-de-puertas-abiertas-medina-sidonia/",
          "title": "Jornadas de Puertas Abiertas, Medina Sidonia archivos - Noticias La Tribuna Hoy"
        },
        {
          "url": "https://news.nationalgeographic.com/news/2014/05/140519-bottom-trawling-seafloor-oceans-damage-science/?beta=true",
          "title": "National Geographic | National Geographic"
        },
        {
          "url": "https://www.nrk.no/urix/",
          "title": "NRK Urix - Utenriksnyheter og -dokumentarer"
        },
        {
          "url": "https://www.sannionews.it/redazione-sannio-news/",
          "title": "Redazione | Sannionews - Sannionews"
        },
        {
          "url": "https://www.wired.com/story/the-pentagon-wants-your-help-analyzing-satellite-images/",
          "title": "xView Detection Challenge: Help the Pentagon Analyze Satellite Images | WIRED"
        }
      ],
      "count": 11
    },
    {
      "name": "company-brand-homepages",
      "bookmarks": [
        {
          "url": "https://www.bmw.com.co/es/index.html?",
          "title": "Tienda BMW Colombia: Carros y Accesorios - BMW Shop Colombia"
        },
        {
          "url": "https://edgewear.com/",
          "title": "EDGEWEAR Reef sandals Oakley sunglasses Shark watches Sanuk - edgewear.com"
        },
        {
          "url": "https://gpay.app.goo.gl/HGxm3Z",
          "title": "Google Pay - Seamlessly Pay Online, Pay In Stores or Send Money"
        },
        {
          "url": "https://iocl.com/",
          "title": "Indian Oil Corporation"
        },
        {
          "url": "https://ireks.pl/historia.htm",
          "title": "IREKS | Polska"
        },
        {
          "url": "https://www.jnj.com/",
          "title": "Johnson & Johnson: Changing health for humanity"
        },
        {
          "url": "https://www.nike.com/t/air-force-1-07-womens-shoes-b19lqD/DD8959-100",
          "title": "Nike Air Force 1 '07 Women's Shoes. Nike.com"
        },
        {
          "url": "https://www.pincergames.com",
          "title": "Pincer Games"
        },
        {
          "url": "https://www.trutv.com/apps",
          "title": "Warner Bros. Discovery"
        }
      ],
      "count": 9
    },
    {
      "name": "arts-culture-media",
      "bookmarks": [
        {
          "url": "https://cool.culturalheritage.org/",
          "title": "Conservation OnLine - CoOL"
        },
        {
          "url": "https://www.si.edu/exhibitions",
          "title": "Current Exhibitions | Smithsonian Institution"
        },
        {
          "url": "https://eastwestplayers.org/",
          "title": "East West Players"
        },
        {
          "url": "https://fantascienza.com",
          "title": "Fantascienza.com"
        },
        {
          "url": "https://www.idagio.com",
          "title": "La meilleure application de streaming de musique classique | IDAGIO"
        },
        {
          "url": "https://capacete.org/nikos-doulos-2/?lang=en",
          "title": "Nikos Doulos | Capacete"
        },
        {
          "url": "https://latraverse.org/Paul-Personne",
          "title": "Paul Personne - La Traverse"
        }
      ],
      "count": 7
    },
    {
      "name": "software-platforms-services",
      "bookmarks": [
        {
          "url": "https://www.and.com",
          "title": "& - The namespace for agents"
        },
        {
          "url": "https://getsupport.apple.com/?caller=psp",
          "title": "Apple Support"
        },
        {
          "url": "https://www.arcgis.com/home/item.html?id=bee5c01ae891442ebd1cf54894939bad",
          "title": "ArcGIS"
        },
        {
          "url": "https://pages.github.com/",
          "title": "GitHub Pages | Websites for you and your projects, hosted directly from your GitHub repository. Just edit, push, and your changes are live."
        },
        {
          "url": "https://www.githubstatus.com",
          "title": "GitHub Status"
        },
        {
          "url": "https://powerapps.microsoft.com/",
          "title": "Microsoft Power Apps - crea app con intelligenza artificiale | Microsoft"
        },
        {
          "url": "https://www.twitch.tv/mozillahubs",
          "title": "Twitch"
        }
      ],
      "count": 7
    },
    {
      "name": "personal-blogs",
      "bookmarks": [
        {
          "url": "https://coder-girls.tumblr.com/",
          "title": "@coder-girls on Tumblr"
        },
        {
          "url": "https://dumspirospero023-blog.tumblr.com/",
          "title": "@dumspirospero023-blog on Tumblr"
        },
        {
          "url": "https://greengryph.tumblr.com/",
          "title": "Green Gryph"
        },
        {
          "url": "https://intothenightphoto.blogspot.com",
          "title": "Into The Night Photography"
        },
        {
          "url": "https://giftsofthejourney.com/2009/12/28/love-in-a-box/",
          "title": "Love In A Box | Gifts Of The Journey"
        },
        {
          "url": "https://unicornshavemohawks.tumblr.com/",
          "title": "@unicornshavemohawks on Tumblr"
        }
      ],
      "count": 6
    },
    {
      "name": "professional-guides-resources",
      "bookmarks": [
        {
          "url": "https://www.webdesignerdepot.com/2021/10/11-must-follow-web-design-blogs/",
          "title": "11 Must-Follow Web Design Blogs"
        },
        {
          "url": "https://www.cisco.com/c/en/us/td/docs/net_mgmt/wae/7-0-1/design/user/guide/WAE_Design_701_User_Guide/wd_701_ug_vpn.html",
          "title": "Cisco WAN Automation Engine (WAE) - Cisco"
        },
        {
          "url": "https://chemistscorner.com/cosmetic-formulation-basics/",
          "title": "Cosmetic Formulation Basics - Chemists Corner"
        },
        {
          "url": "https://library.donorbox.org/",
          "title": "Free Nonprofit Resources, Templates & Checklists By Donorbox Library"
        },
        {
          "url": "https://developer.nvidia.com/blog/",
          "title": "NVIDIA Technical Blog"
        },
        {
          "url": "https://www.sigidwiki.com/wiki/Signal_Identification_Guide",
          "title": "Signal Identification Wiki"
        }
      ],
      "count": 6
    },
    {
      "name": "academic-research-resources",
      "bookmarks": [
        {
          "url": "https://collections.plos.org/s/calls-for-papers",
          "title": "About Collections - PLOS Collections"
        },
        {
          "url": "https://cs.mak.ac.ug/",
          "title": "Department Of Computer Science | Makerere University"
        },
        {
          "url": "https://cs.washington.edu/people/faculty/lazowska/",
          "title": "Ed Lazowska, Professor - Paul G. Allen School of Computer Science & Engineering"
        },
        {
          "url": "https://research.google/pubs/",
          "title": "Publications - Google Research"
        },
        {
          "url": "https://hourofcode.com",
          "title": "Un'ora: Ignite. Ispira. Codice."
        }
      ],
      "count": 5
    },
    {
      "name": "government-public-sector",
      "bookmarks": [
        {
          "url": "https://data.grandlyon.com/",
          "title": "Accueil - data.grandlyon.com"
        },
        {
          "url": "https://www.slovensko.sk/sk/agendy/agenda/_/elektronicka-ziadost",
          "title": "Agenda - UPVS"
        },
        {
          "url": "https://covid19.ca.gov/",
          "title": "COVID-19"
        },
        {
          "url": "https://lannuaire.service-public.fr/grand-est/aube/mairie-10120-01",
          "title": "Mairie - Cussangy - Annuaire | Service Public"
        },
        {
          "url": "https://www.regione.piemonte.it/web/temi/sanita",
          "title": "Sanità | Regione Piemonte"
        }
      ],
      "count": 5
    },
    {
      "name": "sports-leagues-news",
      "bookmarks": [
        {
          "url": "https://www.footballzebras.com/2009/10/how-is-forward-progress-not-stopped-when-player-lands-3-yards-back/",
          "title": "How is forward progress not stopped when player lands 3 yards back? - Football Zebras"
        },
        {
          "url": "https://lakersnation.com/weekly-laker-limelight-derek-fisher/2011/03/22/",
          "title": "Weekly Laker Limelight: Derek Fisher"
        },
        {
          "url": "https://www.nba.com/watch/pricing?",
          "title": "NBA League Pass | Experience Live NBA Games Anytime, Anywhere | NBA.com"
        },
        {
          "url": "https://www.nfl.com/schedules",
          "title": "NFL 2025 - WEEK 6 Schedule | NFL.com"
        },
        {
          "url": "https://www.nfl.com/news/packers-aaron-rodgers-finishes-retreat-addresses-future-i-don-t-want-to-drag-any",
          "title": "Packers' Aaron Rodgers finishes retreat, addresses future: 'I don't want to drag anybody around'"
        }
      ],
      "count": 5
    },
    {
      "name": "data-privacy-policies",
      "bookmarks": [
        {
          "url": "https://securenetsystems.net/mobileapp/app_privacy.html",
          "title": "Mobile App Privacy"
        },
        {
          "url": "https://www.appdicted.com/privacy-policy-for-apps/",
          "title": "Privacy Policy for Apps - Appdicted"
        },
        {
          "url": "https://reverseimagesear.ch/privacy-policy.html",
          "title": "Reverse Image Search"
        },
        {
          "url": "https://www.redditinc.com/policies/user-agreement",
          "title": "User Agreement"
        }
      ],
      "count": 4
    },
    {
      "name": "design-web-development-resources",
      "bookmarks": [
        {
          "url": "https://www.diffchecker.com/",
          "title": "Compare text and find differences online or offline - Diffchecker"
        },
        {
          "url": "https://fontawesome.com/",
          "title": "Font Awesome"
        },
        {
          "url": "https://videojs.com/html5-video-support/",
          "title": "HTML5 Video Support | Video.js"
        },
        {
          "url": "https://www.reshot.com/",
          "title": "Reshot | Free icons & illustrations"
        }
      ],
      "count": 4
    },
    {
      "name": "business-administration-forms",
      "bookmarks": [
        {
          "url": "https://norbchamber.chambermaster.com/eventregistration/register/3250",
          "title": "Event Registration"
        },
        {
          "url": "https://air-loisirs.com/gb/contact-us",
          "title": "Nous contacter"
        },
        {
          "url": "https://cpra-intake-form.target.com",
          "title": "cprarequestform"
        }
      ],
      "count": 3
    },
    {
      "name": "home-products-lifestyle",
      "bookmarks": [
        {
          "url": "https://ruedesmille.com/attimi/carousel-attimo-cuore/",
          "title": "Carousel Attimo Cuore | Rue des Mille"
        },
        {
          "url": "https://www.camicado.com.br/p/jarra-de-vidro-para-cafeteira-oster-programavel-4401/-/A-700041533-br.lc",
          "title": "Jarra de Vidro para Cafeteira Oster Programável 4401 - Camicado"
        },
        {
          "url": "https://urban-beach-house.com/products/carbs-koozie",
          "title": "Urban Beach House"
        }
      ],
      "count": 3
    },
    {
      "name": "leisure-travel-entertainment",
      "bookmarks": [
        {
          "url": "https://www.10best.com/",
          "title": "Best of Travel, Food, & Lifestyle | USA TODAY 10BEST"
        },
        {
          "url": "https://buschgardens.com/williamsburg/roller-coasters/pantheon/",
          "title": "Pantheon - Multi-Launch Coaster | Busch Gardens Williamsburg"
        },
        {
          "url": "https://www.salamanderresort.com/",
          "title": "Salamander Middleburg | Five Star Resort and Spa in Middleburg, VA"
        }
      ],
      "count": 3
    },
    {
      "name": "music-audio-media",
      "bookmarks": [
        {
          "url": "https://www.iheart.com/podcast/1119-people-every-day-76003809/",
          "title": "PEOPLE Every Day | iHeart"
        },
        {
          "url": "https://www.ttbook.org",
          "title": "To The Best Of Our Knowledge | Intelligent. Optimistic. Curious."
        },
        {
          "url": "https://nmpbs.org",
          "title": "New Mexico PBS, KNME-TV - Stream News, Kids, Drama and More"
        }
      ],
      "count": 3
    },
    {
      "name": "online-services-community",
      "bookmarks": [
        {
          "url": "https://radio981.gr/blog/%CE%B4%CE%B9%CE%B1%CE%B2%CE%B1%CF%83%CF%84%CE%B5-34",
          "title": "Account Suspended"
        },
        {
          "url": "https://forum.telldus.com/search.php?search_id=unanswered&sid=59762dda3dee554194f2a4a376936de0",
          "title": "My forum - Unanswered topics"
        },
        {
          "url": "https://www.wireclub.com/",
          "title": "Free Online Chat Rooms - Wireclub"
        }
      ],
      "count": 3
    },
    {
      "name": "personal-wellness-support",
      "bookmarks": [
        {
          "url": "https://www.witchcraftspellslove.com/Astrology-consultancy-service-in-india.php",
          "title": "Astrology consultancy service in India | India"
        },
        {
          "url": "https://www.gofundme.com/f/samantha-cains-medical-and-emergency-expenses?member=25368189&utm_campaign=p_cp+share-sheet&utm_content=undefined&utm_medium=copy_link_all&utm_source=customer&utm_term=undefined",
          "title": "Fundraiser for Macy Gamel by Kalie Clark : Samantha Cain's Emergency Expenses"
        },
        {
          "url": "https://www.nctsn.org/resources/helping-children-with-traumatic-separation-or-traumatic-grief-related-to-covid-19",
          "title": "Helping Children with Traumatic Separation or Traumatic Grief Related to COVID-19 | The National Child Traumatic Stress Network"
        }
      ],
      "count": 3
    },
    {
      "name": "automotive-resources",
      "bookmarks": [
        {
          "url": "https://multi-media.at/?m=201601",
          "title": "Januar 2016 - imago lexis"
        },
        {
          "url": "https://porsche.oemdtc.com",
          "title": "Porsche - OEMDTC"
        }
      ],
      "count": 2
    },
    {
      "name": "business-marketing-tools",
      "bookmarks": [
        {
          "url": "https://www.omni.us/",
          "title": "Omni Channel Outreach System | Omni.us"
        },
        {
          "url": "https://wordpress.com/wp/?",
          "title": "Website Builder | Create Your Site With WordPress | Start Here | WordPress.com"
        }
      ],
      "count": 2
    },
    {
      "name": "economic-finance-data",
      "bookmarks": [
        {
          "url": "https://www.citizensbank.com/disclosures/msstores.aspx",
          "title": "Microsoft Stores | Citizens"
        },
        {
          "url": "https://fred.stlouisfed.org/series/INDPRO",
          "title": "Industrial Production: Total Index (INDPRO) | FRED | St. Louis Fed"
        }
      ],
      "count": 2
    },
    {
      "name": "environmental-sustainability",
      "bookmarks": [
        {
          "url": "https://www.newplasticseconomy.org/projects/global-commitment/signatories",
          "title": "Leading the Transition to a Circular Economy | Ellen MacArthur Foundation"
        },
        {
          "url": "https://rinkiin.fi/",
          "title": "Suomen Pakkauskierrätys RINKI Oy - Rinkiin.fi"
        }
      ],
      "count": 2
    },
    {
      "name": "europe-travel-real-estate",
      "bookmarks": [
        {
          "url": "https://www.citya.com/annonces/vente/appartement/antibes-06004/TAPP459835",
          "title": "Achat/vente immobilière appartement Antibes (06) | Citya Immobilier"
        },
        {
          "url": "https://bilete.cfrcalatori.ro/en-GB/Itineraries",
          "title": "Itineraries + buy - CFR Călători online tickets"
        }
      ],
      "count": 2
    },
    {
      "name": "online-gaming-gambling",
      "bookmarks": [
        {
          "url": "https://xplorela.com/2012/07/20/the-los-angeles-arboretum-botanical-garden/",
          "title": "ANEKA4D | Situs Slot Thailand Paling Gacor Yang Penuh Dengan Pola Gacor"
        },
        {
          "url": "https://alamocitychamber.org/",
          "title": "Casino online en México: bonos sin depósito, bingo y slots"
        }
      ],
      "count": 2
    }
  ],
  "total_bookmarks": 66,
  "num_folders": 23
}