{
  "folders": [
    {
      "name": "company-profile",
      "bookmarks": [
        {
          "url": "https://find-and-update.company-information.service.gov.uk/company/06975984",
          "title": "FULL FACT overview - Find and update company information - GOV.UK"
        },
        {
          "url": "http://www.ganotechnologies.com",
          "title": "Gano Technologies LLC - Home Page"
        },
        {
          "url": "https://chronicle.security/",
          "title": "Google Security Operations | Google Cloud"
        },
        {
          "url": "https://www.pincergames.com",
          "title": "Pincer Games"
        },
        {
          "url": "https://relianceretail.com/reliance-fresh.html",
          "title": "Reliance Retail"
        },
        {
          "url": "https://hk.linkedin.com/company/south-china-morning-post?trk=organization_guest_main-feed-card-text",
          "title": "South China Morning Post SCMP | LinkedIn"
        },
        {
          "url": "https://wideeye.co",
          "title": "Wide Eye / a digital creative agency - web design & branding for mission-driven organizations and nonprofits"
        }
      ],
      "count": 7
    },
    {
      "name": "news-updates",
      "bookmarks": [
        {
          "url": "https://blog.google/inside-google/covid-19/",
          "title": "COVID-19"
        },
        {
          "url": "https://www.latimes.com/entertainment/classichollywood/la-et-st-ca-william-daniels-classic-hollywood-20150510-story.html",
          "title": "Classic Hollywood: In 'Girl Meets World,' William Daniels reprises Mr. Feeny - Los Angeles Times"
        },
        {
          "url": "https://telematics-magazine.com/en/de-minimis-funding-2021-things-to-consider/",
          "title": "De-minimis funding 2021 - what you need to know | Telematics Magazine"
        },
        {
          "url": "https://securityx.space/2016/09/01/electronic-arts-ea-servers-down-poodlecorp-claims-it-ddosed-gaming-giant-hack-read/",
          "title": "Electronic Arts, EA Servers Down? PoodleCorp claims it DDoSed Gaming Giant - Hack Read - securityXspace"
        },
        {
          "url": "https://tuwiazowna.pl/rusza-modernizacja-az-piec-naborow-wnioskow-w-jednym-terminie/",
          "title": "Rusza modernizacja. Aż pięć naborów wniosków w jednym terminie - tuWiązowna.pl"
        }
      ],
      "count": 5
    },
    {
      "name": "nonprofit-human-services",
      "bookmarks": [
        {
          "url": "https://childrensmiraclenetworkhospitals.org",
          "title": "Children's Miracle Network Hospitals"
        },
        {
          "url": "https://hispanicfamilycenter.com/",
          "title": "Healthy Families & Communities - Serving South Jersey since 1976"
        },
        {
          "url": "https://www.ywcahouston.org/",
          "title": "Home"
        },
        {
          "url": "http://www.missingkids.com/home",
          "title": "National Center for Missing & Exploited Children"
        },
        {
          "url": "http://globalneurocare.org/what-we-do/",
          "title": "What We Do - GlobalNeurology®"
        }
      ],
      "count": 5
    },
    {
      "name": "product-shopping",
      "bookmarks": [
        {
          "url": "https://octagonshop.pl/p1423,worek-bokserski-octagon-160x45-standard-gold.html",
          "title": "Oficjalny sklep Octagon - polskiej marki sportowej"
        },
        {
          "url": "https://shakerandspoon.com/",
          "title": "Shaker & Spoon"
        },
        {
          "url": "https://www.all-in-pokershop.cz/all-in_pokershop/eshop/11-1-Studiove-vybaveni-fotopotreby/122-2-Studiove-blesky-prislusenstvi",
          "title": "Studiové blesky"
        },
        {
          "url": "https://www.glamour.com/gallery/taylor-swift-red-lipstick-shop",
          "title": "Taylor Swift's Red Lipstick: Shop Her Favorite Shades | Glamour"
        },
        {
          "url": "https://www.bonkerscorner.com/product-category/women/?utm_source=google&utm_medium=cpc&utm_campaign=brand-ad&gclid=CjwKCAiA7939BRBMEiwA-h",
          "title": "Womens Clothing That Turns Heads: Shop the Latest Trends Now"
        }
      ],
      "count": 5
    },
    {
      "name": "data-reference",
      "bookmarks": [
        {
          "url": "https://reading-not-sleeping.tumblr.com/post/117426794175",
          "title": "codeorg: With all the national debate on... - Reading Not Sleeping"
        },
        {
          "url": "https://ec.europa.eu/eurostat/web/main/data/database",
          "title": "Database - Eurostat"
        },
        {
          "url": "https://apps.who.int/gho/data/node.main.17",
          "title": "legacy"
        },
        {
          "url": "https://uninfo.org/",
          "title": "UNSDG Data Portal"
        }
      ],
      "count": 4
    },
    {
      "name": "education-learning",
      "bookmarks": [
        {
          "url": "http://www.asu.edu",
          "title": "ASU Homepage | Arizona State University"
        },
        {
          "url": "https://www.edreports.org/",
          "title": "EdReports"
        },
        {
          "url": "https://developers.google.com/machine-learning/crash-course",
          "title": "Machine Learning | Google for Developers"
        },
        {
          "url": "https://thestolenidea.tumblr.com/post/89338647405",
          "title": "What % of STEM Should Be Computer Science? - Game Development"
        }
      ],
      "count": 4
    },
    {
      "name": "media-corporate",
      "bookmarks": [
        {
          "url": "https://together.nbcuni.com/advertise/?utm_source=nbc_news&utm_medium=referral&utm_campaign=property_ad_pages",
          "title": "Advertise With Us | NBCUniversal Together"
        },
        {
          "url": "https://www.kansascitypbs.org/kansas-city-pbs-livestream/",
          "title": "Kansas City PBS Livestream"
        },
        {
          "url": "http://TIDAL.com/Beyonc%C3%A9",
          "title": "TIDAL - High Fidelity Music Streaming"
        },
        {
          "url": "http://artists.youtube.com/",
          "title": "YouTube for Artists - Where Music Grows"
        }
      ],
      "count": 4
    },
    {
      "name": "personal-blog",
      "bookmarks": [
        {
          "url": "http://www.ramblingsofadaydreamer.com/2014/05/2014-historic-fiction-reading-challenge.html",
          "title": "Ramblings of a Daydreamer: 2014 Historic Fiction Reading Challenge - May Review Link-Up"
        },
        {
          "url": "http://cinzia1877.blogspot.com/",
          "title": "Parlando e sentendo..."
        },
        {
          "url": "https://blog.acvwilson.me/",
          "title": "puts post"
        },
        {
          "url": "https://babesies.tumblr.com/",
          "title": "void"
        }
      ],
      "count": 4
    },
    {
      "name": "tech-docs",
      "bookmarks": [
        {
          "url": "https://nodejs.org/api/fs.html#fs_promises_api",
          "title": "File system | Node.js v24.10.0 Documentation"
        },
        {
          "url": "https://docs.python.org/3/library/logging.html",
          "title": "logging - Logging facility for Python - Python 3.14.0 documentation"
        },
        {
          "url": "https://git.enlightenment.org/core/efl.git/tree/src/lib/elementary/Efl_Ui.h?id=44bb0c18480f5094fcd0c8be93de87be5c1d78c5",
          "title": "Making sure you're not a bot!"
        },
        {
          "url": "https://docs.videojs.com",
          "title": "Video.js API docs"
        }
      ],
      "count": 4
    },
    {
      "name": "health",
      "bookmarks": [
        {
          "url": "https://disposerx.com/",
          "title": "DisposeRx, Inc. - Safe Medication Solutions - DisposeRx, Inc."
        },
        {
          "url": "https://peopleenespanol.com/chica/skin-cycling-retinol-routine-tiktok/",
          "title": "How the Viral \"Skin Cycling\" Routine Improves Your Skin"
        },
        {
          "url": "https://drsureshmondal.in/andhra-pradesh/hyderabad/ameerpet/Homeopathy-Doctor",
          "title": "Top Homeopathy Doctor in Ameerpet | Dr Sharma (78+)"
        }
      ],
      "count": 3
    },
    {
      "name": "hobby-gaming",
      "bookmarks": [
        {
          "url": "https://boardgamestories.com/artists/marco-primo/",
          "title": "Marco Primo Archives - Boardgame Stories"
        },
        {
          "url": "http://www.dickestel.com/classic2005.htm",
          "title": "Classic Gaming Expo 2005"
        },
        {
          "url": "https://pcper.com/tag/k53/",
          "title": "k53 - PC Perspective"
        }
      ],
      "count": 3
    },
    {
      "name": "marketing",
      "bookmarks": [
        {
          "url": "https://www.inbeat.co/ad-mockup-generator/instagram/",
          "title": "Instagram Ad Mockup"
        },
        {
          "url": "https://docs.google.com/document/d/1fMZ3ZoqhCrKgtf5d3EtznDGZesXBlzPFkvj83U7GHg4/edit#",
          "title": "Instantly.ai Cold Email Quickstart guide - Documenti Google"
        },
        {
          "url": "https://www.hollywoodreporter.com/tip-line",
          "title": "Tip Line | The Hollywood Reporter"
        }
      ],
      "count": 3
    },
    {
      "name": "science",
      "bookmarks": [
        {
          "url": "https://www.ipcc.ch/report/ar6/wg3/",
          "title": "Climate Change 2022: Mitigation of Climate Change"
        },
        {
          "url": "https://www.esa.int/Science_Exploration/Space_Science",
          "title": "ESA - Space Science"
        },
        {
          "url": "http://loop-impact.frontiersin.org/impact/article/514487#views",
          "title": "Loop | Publication Impact |"
        }
      ],
      "count": 3
    },
    {
      "name": "events-calendar",
      "bookmarks": [
        {
          "url": "https://www.renens.ch/web/Culture_et_Loisirs/Agenda/affiche.php?menus_pages_id=14&id=115&id_agendas=337",
          "title": "Agenda - Ville de Renens"
        },
        {
          "url": "https://dakotaathletics.com/main/calendar/caltype/week",
          "title": "Dakota High School Calendar of Events"
        }
      ],
      "count": 2
    },
    {
      "name": "nonprofit-environmental",
      "bookmarks": [
        {
          "url": "http://www.blueprosperity.org",
          "title": "Blue Prosperity Coalition | Global Network Advancing Sustainable Ocean Management"
        },
        {
          "url": "https://www.guyanamarineconservation.org/",
          "title": "Guyana Marine Conservation Society"
        }
      ],
      "count": 2
    },
    {
      "name": "reference-language",
      "bookmarks": [
        {
          "url": "https://www.etymonline.com/",
          "title": "Online Etymology Dictionary"
        },
        {
          "url": "https://www.thesaurus.com/",
          "title": "Synonyms and Antonyms of Words | Thesaurus.com"
        }
      ],
      "count": 2
    },
    {
      "name": "restaurant-info",
      "bookmarks": [
        {
          "url": "https://www.brasseriemaritime.nl/contact/",
          "title": "Contact - Restaurant Brasserie Maritime - Zierikzee"
        },
        {
          "url": "https://www.restavracija123.si/jedilnik/11-6-apetit-verovskova/",
          "title": "Restavracija 123 | 18.2. Apetit Verovškova"
        }
      ],
      "count": 2
    },
    {
      "name": "webdev-tool",
      "bookmarks": [
        {
          "url": "https://bestbuyapis.github.io/bby-query-builder/#/productSearch",
          "title": "Best Buy APIs :: Query Builder"
        },
        {
          "url": "https://coolors.co/contrast-checker/112a46-acc8e5",
          "title": "Color Contrast Checker - Coolors"
        }
      ],
      "count": 2
    },
    {
      "name": "ai-ml-tool",
      "bookmarks": [
        {
          "url": "https://catalog.ngc.nvidia.com/orgs/nvidia/containers/pytorch",
          "title": "GPU-optimized AI, Machine Learning, & HPC Software | NVIDIA NGC"
        }
      ],
      "count": 1
    },
    {
      "name": "corporate-policy",
      "bookmarks": [
        {
          "url": "http://m.target.com/c/target-privacy-policy/-/N-4sr7p",
          "title": "Target Privacy Policy : Target"
        }
      ],
      "count": 1
    },
    {
      "name": "food-recipe",
      "bookmarks": [
        {
          "url": "https://caterbakes.com/",
          "title": "Caterbakes By Chef Wale - Food Recipe. Food Business. Food Health"
        }
      ],
      "count": 1
    },
    {
      "name": "hobby-fandom",
      "bookmarks": [
        {
          "url": "http://www.whedon.info/index.php/gahlery/trainingsraum/dist/dist/IMG/jpg/-Graphics,395-.html?debut_articles=50",
          "title": "Joss Whedon : Buffy, Angel, Firefly, Dollhouse, Avengers - Page 50"
        }
      ],
      "count": 1
    },
    {
      "name": "job-board",
      "bookmarks": [
        {
          "url": "https://jobs.accaglobal.com/?utm_source=ACCAglobal&utm_medium=referral&utm_campaign=navbar1",
          "title": "ACCA Careers | jobs | Choose from 26,089 live vacancies"
        }
      ],
      "count": 1
    },
    {
      "name": "social-chat",
      "bookmarks": [
        {
          "url": "http://b-gay.com/chat/",
          "title": "Free Gay Chat - Online Chat Rooms for Men - B-Gay.com"
        }
      ],
      "count": 1
    },
    {
      "name": "travel-planning",
      "bookmarks": [
        {
          "url": "https://www.mvg.de/tickets-tarife.html",
          "title": "Abos & Tickets der MVG | MVG"
        }
      ],
      "count": 1
    }
  ],
  "total_bookmarks": 71,
  "num_folders": 25
}